<?xml version="1.0" encoding="utf-8"?>
<Defs>

  <!--
    Job: El mecanoid camina hacia la repair station y se acopla.

    FIX E: checkOverrideOnDamage cambiado de true a false.
    Con true, cada golpe recibido mientras el mecanoid caminaba hacia la station
    provocaba que RimWorld reevaluara el job, cancelando GoToRepairStation en
    combate — exactamente cuando más se necesita la reparación. El think tree
    le reasignaba el mismo job en el siguiente tick, creando un loop visible
    en el log y haciendo la feature inutilizable bajo fuego enemigo.
    false es consistente con RRS_RepairAtStation (el mecanoid ignora el daño
    mientras navega hacia la station, igual que cuando ya está docked).
  -->
  <JobDef>
    <defName>RRS_GoToRepairStation</defName>
    <label>go to repair station</label>
    <description>Go to a robot repair station for self-repair.</description>
    <driverClass>RobotRepairStation.JobDriver_GoToRepairStation</driverClass>
    <reportString>going to repair station.</reportString>
    <allowOpportunisticPrefix>false</allowOpportunisticPrefix>
    <playerInterruptible>true</playerInterruptible>
    <checkOverrideOnDamage>false</checkOverrideOnDamage>
  </JobDef>

  <!-- Job: El mecanoid está docked y siendo reparado -->
  <JobDef>
    <defName>RRS_RepairAtStation</defName>
    <label>repairing at station</label>
    <description>Being repaired at the robot repair station.</description>
    <driverClass>RobotRepairStation.JobDriver_RepairAtStation</driverClass>
    <reportString>repairing at station.</reportString>
    <allowOpportunisticPrefix>false</allowOpportunisticPrefix>
    <playerInterruptible>true</playerInterruptible>
    <checkOverrideOnDamage>false</checkOverrideOnDamage>
    <casualInterruptible>false</casualInterruptible>
  </JobDef>

</Defs>
